README.md
setup.py
yadown/__init__.py
yadown/cmd.py
yadown/main.py
yadown.egg-info/PKG-INFO
yadown.egg-info/SOURCES.txt
yadown.egg-info/dependency_links.txt
yadown.egg-info/entry_points.txt
yadown.egg-info/top_level.txt