Metadata-Version: 1.0
Name: yadown
Version: 0.0.1
Summary: YADOWN: YAndex disk DOWNloader
Home-page: UNKNOWN
Author: UNKNOWN
Author-email: UNKNOWN
License: MIT
Platform: UNKNOWN
